[
{
  "model": "courses.subject",
  "pk": 1,
  "fields": {
    "title": "computer-sciece",
    "slug": "computer-sciece"
  }
},
{
  "model": "courses.subject",
  "pk": 2,
  "fields": {
    "title": "algorithms and data structures",
    "slug": "algorithms-and-data-structures"
  }
},
{
  "model": "courses.subject",
  "pk": 3,
  "fields": {
    "title": "artificial intelligence",
    "slug": "artificial-intelligence"
  }
},
{
  "model": "courses.subject",
  "pk": 4,
  "fields": {
    "title": "operating systems",
    "slug": "operating-systems"
  }
}
]
